pyvapor/__init__.py
pyvapor/dbg.py
pyvapor/vaporfunc.py
vaporup-1.0.3.data/scripts/vapor.py
vaporup-1.0.3.dist-info/licenses/LICENSE
vaporup-1.0.3.dist-info/METADATA
vaporup-1.0.3.dist-info/WHEEL
vaporup-1.0.3.dist-info/top_level.txt
vaporup-1.0.3.dist-info/RECORD
