Metadata-Version: 2.4
Name: vaporup
Version: 1.0.3
Summary: Vapor is a tool for classification of Influenza samples from short read sequence data, which can be apllied also to other viruses.
Author: Joel Southgate
Maintainer-email: Wolfgang Maier <maierw@informatik.uni-freiburg.de>
License-Expression: GPL-3.0-or-later
Project-URL: Homepage, https://github.com/wm75/vaporup
Keywords: virology
Classifier: Programming Language :: Python :: 3
Classifier: Development Status :: 4 - Beta
Classifier: Operating System :: OS Independent
Classifier: Topic :: Scientific/Engineering
Classifier: Topic :: Scientific/Engineering :: Bio-Informatics
Classifier: Intended Audience :: Science/Research
Classifier: Natural Language :: English
Requires-Python: >=3.8
License-File: LICENSE
Requires-Dist: numpy>=1.15.1
Dynamic: license-file
